setup.py
h5gments/__init__.py
h5gments/formatter.py
h5gments/formatters.py
h5gments/lexer.py
h5gments/lexers.py
h5gments.egg-info/PKG-INFO
h5gments.egg-info/SOURCES.txt
h5gments.egg-info/dependency_links.txt
h5gments.egg-info/requires.txt
h5gments.egg-info/top_level.txt