Metadata-Version: 1.0
Name: h5gments
Version: 0.1.32
Summary: html5高亮库
Home-page: https://code.xueersi.com
Author: Ruoyu Wang
Author-email: UNKNOWN
License: UNKNOWN
Platform: UNKNOWN
